LICENSE
MANIFEST.in
README.md
pyproject.toml
requirements.txt
setup.py
bev/__init__.py
bev/__version__.py
bev/compat.py
bev/exceptions.py
bev/hash.py
bev/hookspecs.py
bev/interface.py
bev/local.py
bev/ops.py
bev/py.typed
bev/shortcuts.py
bev/testing.py
bev/utils.py
bev/vc.py
bev/wc.py
bev.egg-info/PKG-INFO
bev.egg-info/SOURCES.txt
bev.egg-info/dependency_links.txt
bev.egg-info/entry_points.txt
bev.egg-info/requires.txt
bev.egg-info/top_level.txt
bev/cli/__init__.py
bev/cli/add.py
bev/cli/app.py
bev/cli/blame.py
bev/cli/entrypoint.py
bev/cli/fetch.py
bev/cli/init.py
bev/cli/pull.py
bev/cli/storage.py
bev/cli/utils.py
bev/config/__init__.py
bev/config/base.py
bev/config/compat.py
bev/config/hostname.py
bev/config/include.py
bev/config/location.py
bev/config/parse.py
bev/config/registry.py
bev/config/remote.py
bev/config/utils.py
tests/test_add.py
tests/test_cli.py
tests/test_config.py
tests/test_hash_signature.py
tests/test_interface.py
tests/test_ops.py
tests/test_registry.py
tests/test_vc.py