Metadata-Version: 2.4
Name: bev
Version: 0.13.1
Summary: A small manager for versioned data
Home-page: https://github.com/neuro-ml/bev
Download-URL: https://github.com/neuro-ml/bev/archive/v0.13.1.tar.gz
Author-email: Max <max@ira-labs.com>, Talgat <t.saparov@ira-labs.com>
License:                                  Apache License
Project-URL: Homepage, https://github.com/neuro-ml/bev
Project-URL: Issues, https://github.com/neuro-ml/bev/issues
Project-URL: Source, https://github.com/neuro-ml/bev
Project-URL: Docs, https://neuro-ml.github.io/bev
Keywords: data,version control
Classifier: Development Status :: 5 - Production/Stable
Classifier: License :: OSI Approved :: Apache Software License
Classifier: Programming Language :: Python :: 3
Classifier: Programming Language :: Python :: 3.9
Classifier: Programming Language :: Python :: 3.10
Classifier: Programming Language :: Python :: 3.11
Classifier: Programming Language :: Python :: 3.12
Classifier: Programming Language :: Python :: 3.13
Classifier: Programming Language :: Python :: 3 :: Only
Requires-Python: >=3.7
License-File: LICENSE
Requires-Dist: wcmatch<10.1,>=10.0
Requires-Dist: pyyaml
Requires-Dist: paramiko
Requires-Dist: tqdm
Requires-Dist: tarn<1.0.0,>=0.14.2
Requires-Dist: pydantic
Requires-Dist: typer<1.0.0,>=0.9.0
Requires-Dist: rich
Requires-Dist: jboc<1.0.0
Requires-Dist: humanfriendly
Requires-Dist: typing_extensions
Requires-Dist: pytimeparse
Dynamic: download-url
Dynamic: home-page
Dynamic: license-file
Dynamic: requires-python
